dlt_utils/__init__.py
dlt_utils/dlt_metadata_receiver.py
dlt_utils/dlt_transformations.py
dlt_utils/main_cdc_utils.py
tests/__init__.py
tests/conftest.py
tests/test_transformation_module.py
dlt_utils_lib-1.1.6.dist-info/METADATA
dlt_utils_lib-1.1.6.dist-info/WHEEL
dlt_utils_lib-1.1.6.dist-info/top_level.txt
dlt_utils_lib-1.1.6.dist-info/RECORD
