Metadata-Version: 2.1
Name: dlt-utils-lib
Version: 1.1.6
Summary: UNKNOWN
Home-page: UNKNOWN
License: UNKNOWN
Platform: UNKNOWN
Requires-Dist: pyspark
Requires-Dist: delta-spark
Provides-Extra: dev
Requires-Dist: pytest; extra == "dev"
